lucyna/__init__.py
lucyna/cli.py
lucyna/context.py
lucyna/data_loader.py
lucyna/exception.py
lucyna/plugins/__init__.py
lucyna/plugins/ecs/__init__.py
lucyna/plugins/ecs/cluster/__init__.py
lucyna/plugins/ecs/cluster/commands.py
lucyna/plugins/ecs/cluster/data.py
lucyna/plugins/ecs/cluster/layouts.py
lucyna/plugins/ecs/data.py
lucyna/plugins/ecs/service/__init__.py
lucyna/plugins/ecs/service/commands.py
lucyna/plugins/ecs/service/data.py
lucyna/plugins/ecs/service/layouts.py
lucyna/plugins/ecs/task/__init__.py
lucyna/plugins/ecs/task/commands.py
lucyna/plugins/ecs/task/data.py
lucyna/plugins/ecs/task/layouts.py
lucyna/plugins/ecs/ui.py
lucyna/plugins/lambda_function/__init__.py
lucyna/plugins/lambda_function/commands.py
lucyna/plugins/lambda_function/data.py
lucyna/plugins/lambda_function/layouts.py
lucyna/runner.py
lucyna/ui.py
lucyna/utils.py
lucyna-0.11.2.dist-info/entry_points.txt
lucyna-0.11.2.dist-info/LICENSE
lucyna-0.11.2.dist-info/WHEEL
lucyna-0.11.2.dist-info/METADATA
lucyna-0.11.2.dist-info/RECORD
