Metadata-Version: 2.1
Name: lucyna
Version: 0.11.2
Summary: Lucyna is a library that tries to help you with your daily tasks with AWS ECS and AWS Lambda (more might come in future).
Home-page: https://github.com/whisller/lucyna
License: MIT
Keywords: aws,ecs,cli,lambda
Author: Daniel Ancuta
Author-email: whisller@gmail.com
Requires-Python: >=3.8,<4.0
Classifier: Development Status :: 4 - Beta
Classifier: Environment :: Console
Classifier: Intended Audience :: Developers
Classifier: License :: OSI Approved :: MIT License
Classifier: Operating System :: OS Independent
Classifier: Programming Language :: Python
Classifier: Programming Language :: Python :: 3
Classifier: Programming Language :: Python :: 3 :: Only
Classifier: Programming Language :: Python :: 3.8
Requires-Dist: arrow (>=1.1.0,<2.0.0)
Requires-Dist: asciiplot (>=0.1.7,<0.2.0)
Requires-Dist: boto3 (>=1.18,<2.0)
Requires-Dist: click (>=8.0,<9.0)
Requires-Dist: click-log (>=0.3.2,<0.4.0)
Requires-Dist: loguru (>=0.5.3,<0.6.0)
Requires-Dist: rich (>=10.3.0,<11.0.0)
Project-URL: Repository, https://github.com/whisller/lucyna
